llmchat/__init__.py
llmchat/main.py
pyllmchat-1.0.0.dist-info/METADATA
pyllmchat-1.0.0.dist-info/WHEEL
pyllmchat-1.0.0.dist-info/top_level.txt
pyllmchat-1.0.0.dist-info/RECORD
